Anti_Viral_Protocol-1.0.1.data/data/resources/2x_off.png
Anti_Viral_Protocol-1.0.1.data/data/resources/2x_on.png
Anti_Viral_Protocol-1.0.1.data/data/resources/Credits.ogg
Anti_Viral_Protocol-1.0.1.data/data/resources/DJB Get Digital.ttf
Anti_Viral_Protocol-1.0.1.data/data/resources/Ending.ogg
Anti_Viral_Protocol-1.0.1.data/data/resources/ExitButton.png
Anti_Viral_Protocol-1.0.1.data/data/resources/Explode.wav
Anti_Viral_Protocol-1.0.1.data/data/resources/GameIcon_32.png
Anti_Viral_Protocol-1.0.1.data/data/resources/GameIcon_64.png
Anti_Viral_Protocol-1.0.1.data/data/resources/HelpButton.png
Anti_Viral_Protocol-1.0.1.data/data/resources/Main_Menu.ogg
Anti_Viral_Protocol-1.0.1.data/data/resources/RPG.wav
Anti_Viral_Protocol-1.0.1.data/data/resources/Shoot_AR_1.wav
Anti_Viral_Protocol-1.0.1.data/data/resources/Shoot_Pistol_1.wav
Anti_Viral_Protocol-1.0.1.data/data/resources/Shotgun.wav
Anti_Viral_Protocol-1.0.1.data/data/resources/StartButton.png
Anti_Viral_Protocol-1.0.1.data/data/resources/ar_2x_L.png
Anti_Viral_Protocol-1.0.1.data/data/resources/ar_2x_R.png
Anti_Viral_Protocol-1.0.1.data/data/resources/ar_L.png
Anti_Viral_Protocol-1.0.1.data/data/resources/ar_R.png
Anti_Viral_Protocol-1.0.1.data/data/resources/bg_bottom.png
Anti_Viral_Protocol-1.0.1.data/data/resources/bg_top.png
Anti_Viral_Protocol-1.0.1.data/data/resources/bossbar.png
Anti_Viral_Protocol-1.0.1.data/data/resources/credits.png
Anti_Viral_Protocol-1.0.1.data/data/resources/damage.png
Anti_Viral_Protocol-1.0.1.data/data/resources/endgame.png
Anti_Viral_Protocol-1.0.1.data/data/resources/endgate.png
Anti_Viral_Protocol-1.0.1.data/data/resources/explosion.png
Anti_Viral_Protocol-1.0.1.data/data/resources/game-over.png
Anti_Viral_Protocol-1.0.1.data/data/resources/gun_ar.png
Anti_Viral_Protocol-1.0.1.data/data/resources/gun_pistol.png
Anti_Viral_Protocol-1.0.1.data/data/resources/gun_rpg.png
Anti_Viral_Protocol-1.0.1.data/data/resources/gun_shotgun.png
Anti_Viral_Protocol-1.0.1.dist-info/LICENSE
Anti_Viral_Protocol-1.0.1.dist-info/METADATA
Anti_Viral_Protocol-1.0.1.dist-info/WHEEL
Anti_Viral_Protocol-1.0.1.dist-info/entry_points.txt
Anti_Viral_Protocol-1.0.1.dist-info/top_level.txt
Anti_Viral_Protocol-1.0.1.dist-info/RECORD
