Metadata-Version: 2.1
Name: Anti-Viral-Protocol
Version: 1.0.1
Summary: 2d platformer, side scroller game
Home-page: https://github.com/Team-De-bug/Anti-Viral-Protocol
Author: marudhu
Author-email: marudhupaandian@gmail.com
License: UNKNOWN
Platform: UNKNOWN
Classifier: Programming Language :: Python :: 3.6
Classifier: Programming Language :: Python :: 3.7
Classifier: Topic :: Games/Entertainment
Classifier: Topic :: Games/Entertainment :: Side-Scrolling/Arcade Games
Classifier: Operating System :: OS Independent
Classifier: License :: OSI Approved :: GNU General Public License v3 (GPLv3)
Requires-Python: >=3.6
Requires-Dist: pygame
